mlx_lm_omni/__init__.py
mlx_lm_omni/audio_mel.py
mlx_lm_omni/py.typed
mlx_lm_omni/tokenizer.py
mlx_lm_omni/utils.py
mlx_lm_omni/models/__init__.py
mlx_lm_omni/models/qwen_omni/__init__.py
mlx_lm_omni/models/qwen_omni/audio_tower.py
mlx_lm_omni/models/qwen_omni/model.py
mlx_lm_omni/models/qwen_omni/thinker.py
mlx_lm_omni/models/ultravox/__init__.py
mlx_lm_omni/models/ultravox/audio_tower.py
mlx_lm_omni/models/ultravox/model.py
mlx_lm_omni/models/ultravox/projector.py
mlx_lm_omni/models/ultravox/thinker.py
mlx_lm_omni-0.1.3.dist-info/METADATA
mlx_lm_omni-0.1.3.dist-info/WHEEL
mlx_lm_omni-0.1.3.dist-info/RECORD
