Metadata-Version: 2.4
Name: mlx-lm-omni
Version: 0.1.3
Summary: Add your description here
Author-email: Giang Minh <giang.ndm@gmail.com>
Requires-Python: >=3.11
Requires-Dist: mlx-lm>=0.24.0
Requires-Dist: mlx>=0.25.1
